Metadata-Version: 2.1
Name: odoo-addon-account-menu-invoice-refund
Version: 16.0.1.0.1.6
Summary: New invoice menu that combine invoices and refunds
Home-page: https://github.com/OCA/account-invoicing
Author: Ecosoft, Odoo Community Association (OCA)
Author-email: support@odoo-community.org
License: AGPL-3
Platform: UNKNOWN
Classifier: Programming Language :: Python
Classifier: Framework :: Odoo
Classifier: Framework :: Odoo :: 16.0
Classifier: License :: OSI Approved :: GNU Affero General Public License v3
Classifier: Development Status :: 4 - Beta
Requires-Python: >=3.10
Requires-Dist: odoo <16.1dev,>=16.0a
